<?xml version="1.0" encoding="utf-8" ?>
<dwsync>
<file name=".gitignore" server="10.43.5.9//users/darekrossman/documents/code/valpak-solr/" local="130114036450000000" remote="130114036450000000" Dst="2" />
<file name="bower.json" server="10.43.5.9//users/darekrossman/documents/code/valpak-solr/" local="130114036450000000" remote="130114036450000000" Dst="2" />
<file name="component.json" server="10.43.5.9//users/darekrossman/documents/code/valpak-solr/" local="130114036450000000" remote="130114036450000000" Dst="2" />
<file name="composer.json" server="10.43.5.9//users/darekrossman/documents/code/valpak-solr/" local="130114036450000000" remote="130114036450000000" Dst="2" />
<file name="jquery-migrate.js" server="10.43.5.9//users/darekrossman/documents/code/valpak-solr/" local="130114036450000000" remote="130114036450000000" Dst="2" />
<file name="jquery-migrate.min.js" server="10.43.5.9//users/darekrossman/documents/code/valpak-solr/" local="130114036450000000" remote="130114036450000000" Dst="2" />
<file name="jquery.js" server="10.43.5.9//users/darekrossman/documents/code/valpak-solr/" local="130114036450000000" remote="130114036450000000" Dst="2" />
<file name="jquery.min.js" server="10.43.5.9//users/darekrossman/documents/code/valpak-solr/" local="130114036450000000" remote="130114036450000000" Dst="2" />
<file name="package.json" server="10.43.5.9//users/darekrossman/documents/code/valpak-solr/" local="130114036450000000" remote="130114036450000000" Dst="2" />
<file name="README.md" server="10.43.5.9//users/darekrossman/documents/code/valpak-solr/" local="130114036450000000" remote="130114036450000000" Dst="2" />
</dwsync>